LICENSE
README.rst
setup.py
rapid/__init__.py
rapid/__main__.py
rapid/configuration_generator.py
rapid/ci/__init__.py
rapid/ci/ci_controller.py
rapid/ci/data/__init__.py
rapid/ci/data/commit_dal.py
rapid/ci/data/github_dal.py
rapid/ci/data/models.py
rapid/ci/services/__init__.py
rapid/ci/services/vcs_service.py
rapid/ci/vcs/__init__.py
rapid/ci/vcs/github_controller.py
rapid/client/__init__.py
rapid/client/action_instance_runner.py
rapid/client/client_configuration.py
rapid/client/client_upgrader.py
rapid/client/executor.py
rapid/client/communicator/__init__.py
rapid/client/communicator/client_communicator.py
rapid/client/controllers/__init__.py
rapid/client/controllers/main.py
rapid/client/controllers/work_controller.py
rapid/client/parsers/__init__.py
rapid/client/parsers/abstract_parser.py
rapid/client/parsers/tap_parser.py
rapid/client/parsers/xunit_parser.py
rapid/extensions/__init__.py
rapid/extensions/extension_loader.py
rapid/lib/__init__.py
rapid/lib/base_controller.py
rapid/lib/communication.py
rapid/lib/communicator.py
rapid/lib/configuration.py
rapid/lib/constants.py
rapid/lib/converters.py
rapid/lib/exceptions.py
rapid/lib/features.py
rapid/lib/filters.py
rapid/lib/in_memory_store.py
rapid/lib/log_server.py
rapid/lib/modules.py
rapid/lib/queue_handler_constants.py
rapid/lib/results_serializer.py
rapid/lib/store_service.py
rapid/lib/utils.py
rapid/lib/version.py
rapid/lib/work_request.py
rapid/lib/wrapping_thread_pool.py
rapid/lib/framework/__init__.py
rapid/lib/framework/injectable.py
rapid/lib/framework/ioc.py
rapid/log_server/__init__.py
rapid/master/__init__.py
rapid/master/master_configuration.py
rapid/master/communicator/__init__.py
rapid/master/communicator/client.py
rapid/master/communicator/master_communicator.py
rapid/master/controllers/__init__.py
rapid/master/controllers/api/__init__.py
rapid/master/controllers/api/files_controller.py
rapid/master/controllers/api/upgrade_controller.py
rapid/master/controllers/api/utility_controller.py
rapid_framework.egg-info/PKG-INFO
rapid_framework.egg-info/SOURCES.txt
rapid_framework.egg-info/dependency_links.txt
rapid_framework.egg-info/entry_points.txt
rapid_framework.egg-info/requires.txt
rapid_framework.egg-info/top_level.txt
