Metadata-Version: 2.1
Name: rapid-framework
Version: 23.831.103159
Summary: Rapid Framework
Home-page: https://github.com/BambooHR/rapid
Author: Michael Bright
Author-email: mbright@bamboohr.com
License: UNKNOWN
Keywords: internal ci jenkinskiller
Platform: UNKNOWN
Classifier: Development Status :: 4 - Beta
Classifier: Topic :: Software Development :: Build Tools
Classifier: Programming Language :: Python :: 2.7
Provides-Extra: test
Provides-Extra: master
Provides-Extra: windows-client
Provides-Extra: client
